processpdfdocs/__init__.py
processpdfdocs/download_models.py
processpdfdocs/processor.py
processpdfdocs/utils.py
processpdfdocs/models/cell_detect_model.pt
processpdfdocs/models/rotation_model.onnx
processpdfdocs/models/table_detect_model.pt
processpdfdocs-0.0.12.11.dist-info/METADATA
processpdfdocs-0.0.12.11.dist-info/WHEEL
processpdfdocs-0.0.12.11.dist-info/licenses/LICENSE
processpdfdocs-0.0.12.11.dist-info/RECORD
